MANIFEST.in
README.rst
setup.cfg
setup.py
django_box/__init__.py
django_box/apps.py
django_box.egg-info/PKG-INFO
django_box.egg-info/SOURCES.txt
django_box.egg-info/dependency_links.txt
django_box.egg-info/not-zip-safe
django_box.egg-info/top_level.txt
django_box/templates/box_base.html